{
  "_class": "group",
  "do_objectID": "50FDD1BB-AB13-477C-B75E-53A4BF20C77C",
  "exportOptions": {
    "_class": "exportOptions",
    "exportFormats": [
    ],
    "includedLayerIds": [
    ],
    "layerOptions": 0,
    "shouldTrim": false
  },
  "frame": {
    "_class": "rect",
    "constrainProportions": false,
    "height": 36,
    "width": 36,
    "x": 142,
    "y": 27
  },
  "hasClickThrough": false,
  "isFlippedHorizontal": false,
  "isFlippedVertical": false,
  "isLocked": false,
  "isVisible": true,
  "layerListExpandedType": 0,
  "layers": [
    {
      "class": "shapeGroup",
      "id": "4126C542-85A7-47D6-BA5E-F854A44FD1BF"
    },
    {
      "class": "shapeGroup",
      "id": "9999CD96-9270-47B3-BA4F-B07464B19ADD"
    }
  ],
  "name": "logo_white",
  "nameIsFixed": true,
  "resizingConstraint": 63,
  "resizingType": 0,
  "rotation": 0,
  "shouldBreakMaskChain": false,
  "style": {
    "_class": "style",
    "blur": {
      "_class": "blur",
      "center": "{0.5, 0.5}",
      "isEnabled": false,
      "motionAngle": 0,
      "radius": 24.00000035762787,
      "type": 0
    },
    "endDecorationType": 0,
    "miterLimit": 10,
    "startDecorationType": 0
  },
  "userInfo": {
    "com.animaapp.stc-sketch-plugin": {
      "kModelPropertiesKey": {
      }
    },
    "com.invisionlabs.library": {
      "original-layer": {
        "originalID": "0A045AAF-79BB-4393-BE8B-99811A4444D0",
        "version": 2
      }
    }
  }
}