{
  "_class": "shapeGroup",
  "clippingMaskMode": 0,
  "do_objectID": "103F6BC6-512F-4568-8E96-5703EAA10E78",
  "exportOptions": {
    "_class": "exportOptions",
    "exportFormats": [
    ],
    "includedLayerIds": [
    ],
    "layerOptions": 0,
    "shouldTrim": false
  },
  "frame": {
    "_class": "rect",
    "constrainProportions": false,
    "height": 11.06542056074765,
    "width": 7.999999999999988,
    "x": 14,
    "y": 24.89719626168225
  },
  "hasClickThrough": false,
  "hasClippingMask": false,
  "isFlippedHorizontal": false,
  "isFlippedVertical": false,
  "isLocked": false,
  "isVisible": true,
  "layerListExpandedType": 0,
  "layers": [
    {
      "class": "shapePath",
      "id": "8B54665D-9987-4049-8C07-F116D1560E4F"
    }
  ],
  "name": "label-arrow",
  "nameIsFixed": false,
  "resizingConstraint": 63,
  "resizingType": 0,
  "rotation": 0,
  "shouldBreakMaskChain": false,
  "style": {
    "sharedObjectID": "ED924894-CF73-4B29-83E4-1210B388DAA1"
  },
  "windingRule": 1
}