{
  "_class": "shapeGroup",
  "clippingMaskMode": 0,
  "do_objectID": "C5E57C04-14C6-45B8-95E7-11049255B180",
  "exportOptions": {
    "_class": "exportOptions",
    "exportFormats": [
    ],
    "includedLayerIds": [
    ],
    "layerOptions": 0,
    "shouldTrim": false
  },
  "frame": {
    "_class": "rect",
    "constrainProportions": false,
    "height": 12.79631363636365,
    "width": 13.74195454545455,
    "x": 0.2270545454545315,
    "y": 0.2036863636363636
  },
  "hasClickThrough": false,
  "hasClippingMask": true,
  "isFlippedHorizontal": false,
  "isFlippedVertical": false,
  "isLocked": false,
  "isVisible": true,
  "layerListExpandedType": 0,
  "layers": [
    {
      "class": "shapePath",
      "id": "6DA11D3F-5386-4A85-A7B5-79862650B531"
    }
  ],
  "name": "Clip 5",
  "nameIsFixed": false,
  "resizingConstraint": 63,
  "resizingType": 0,
  "rotation": 0,
  "shouldBreakMaskChain": false,
  "style": {
    "_class": "style",
    "endDecorationType": 0,
    "miterLimit": 10,
    "startDecorationType": 0
  },
  "windingRule": 1
}