{
  "_class": "shapeGroup",
  "clippingMaskMode": 0,
  "do_objectID": "CDC137DE-7A28-4F10-B9D3-749BE8F72486",
  "exportOptions": {
    "_class": "exportOptions",
    "exportFormats": [
    ],
    "includedLayerIds": [
    ],
    "layerOptions": 0,
    "shouldTrim": false
  },
  "frame": {
    "_class": "rect",
    "constrainProportions": false,
    "height": 5,
    "width": 1,
    "x": 11,
    "y": 27
  },
  "hasClickThrough": false,
  "hasClippingMask": false,
  "isFlippedHorizontal": false,
  "isFlippedVertical": false,
  "isLocked": false,
  "isVisible": true,
  "layerListExpandedType": 0,
  "layers": [
    {
      "class": "rectangle",
      "id": "02A14AC4-0881-4178-BC8B-76E81804EC21"
    }
  ],
  "name": "start",
  "nameIsFixed": false,
  "resizingConstraint": 63,
  "resizingType": 0,
  "rotation": 0,
  "shouldBreakMaskChain": false,
  "style": {
    "sharedObjectID": "0285CD66-2E4D-4098-990B-D044A8B759F0"
  },
  "windingRule": 1
}