{
  "_class": "group",
  "do_objectID": "F4FAE9CB-2B3C-448F-BE3D-D86F742B5158",
  "exportOptions": {
    "_class": "exportOptions",
    "exportFormats": [
    ],
    "includedLayerIds": [
    ],
    "layerOptions": 0,
    "shouldTrim": false
  },
  "frame": {
    "_class": "rect",
    "constrainProportions": false,
    "height": 48,
    "width": 47,
    "x": 293,
    "y": 0
  },
  "hasClickThrough": false,
  "isFlippedHorizontal": false,
  "isFlippedVertical": false,
  "isLocked": false,
  "isVisible": true,
  "layerListExpandedType": 0,
  "layers": [
    {
      "class": "text",
      "id": "B2BFFEA7-C550-44D5-B328-891FDDEEDAAC"
    },
    {
      "class": "shapeGroup",
      "id": "C5573995-67E2-4F02-B637-D5ECC5EF75DB"
    },
    {
      "class": "symbolInstance",
      "id": "27B41DBC-682F-402B-9461-34E2FE45DAD1"
    }
  ],
  "name": "Group 3",
  "nameIsFixed": false,
  "resizingConstraint": 63,
  "resizingType": 0,
  "rotation": 0,
  "shouldBreakMaskChain": false,
  "style": {
    "_class": "style",
    "endDecorationType": 0,
    "miterLimit": 10,
    "startDecorationType": 0
  }
}