{
  "_class": "group",
  "do_objectID": "4314E4D5-C7C7-497A-A67B-C16607926A22",
  "exportOptions": {
    "_class": "exportOptions",
    "exportFormats": [
    ],
    "includedLayerIds": [
    ],
    "layerOptions": 0,
    "shouldTrim": false
  },
  "frame": {
    "_class": "rect",
    "constrainProportions": false,
    "height": 41.92708333333333,
    "width": 32.00000000000001,
    "x": 187,
    "y": 0
  },
  "hasClickThrough": false,
  "isFlippedHorizontal": false,
  "isFlippedVertical": false,
  "isLocked": false,
  "isVisible": true,
  "layerListExpandedType": 0,
  "layers": [
    {
      "class": "shapeGroup",
      "id": "76A2C500-06B1-4FE2-8D84-012FA993294A"
    },
    {
      "class": "text",
      "id": "B9C158D8-FA48-4CF3-B939-44ECBD56F7B2"
    }
  ],
  "name": "Y",
  "nameIsFixed": true,
  "resizingConstraint": 63,
  "resizingType": 0,
  "rotation": 0,
  "shouldBreakMaskChain": false,
  "style": {
    "_class": "style",
    "endDecorationType": 0,
    "miterLimit": 10,
    "startDecorationType": 0
  }
}