{
  "_class": "shapeGroup",
  "clippingMaskMode": 0,
  "do_objectID": "4EF62FDE-E995-4589-9109-7C29F7104A2F",
  "exportOptions": {
    "_class": "exportOptions",
    "exportFormats": [
    ],
    "includedLayerIds": [
    ],
    "layerOptions": 0,
    "shouldTrim": false
  },
  "frame": {
    "_class": "rect",
    "constrainProportions": false,
    "height": 32,
    "width": 1,
    "x": 40,
    "y": 0
  },
  "hasClickThrough": false,
  "hasClippingMask": false,
  "isFlippedHorizontal": false,
  "isFlippedVertical": false,
  "isLocked": false,
  "isVisible": true,
  "layerListExpandedType": 0,
  "layers": [
    {
      "class": "rectangle",
      "id": "D5959F76-351E-431E-9B87-B124FC0B3A04"
    }
  ],
  "name": "line",
  "nameIsFixed": false,
  "resizingConstraint": 63,
  "resizingType": 0,
  "rotation": 0,
  "shouldBreakMaskChain": false,
  "style": {
    "sharedObjectID": "0285CD66-2E4D-4098-990B-D044A8B759F0"
  },
  "windingRule": 1
}