{
  "_class": "shapeGroup",
  "clippingMaskMode": 0,
  "do_objectID": "92FF95E7-725F-4626-9CC4-99A15C78A155",
  "exportOptions": {
    "_class": "exportOptions",
    "exportFormats": [
    ],
    "includedLayerIds": [
    ],
    "layerOptions": 0,
    "shouldTrim": false
  },
  "frame": {
    "_class": "rect",
    "constrainProportions": false,
    "height": 13,
    "width": 14,
    "x": 14,
    "y": 6
  },
  "hasClickThrough": false,
  "hasClippingMask": false,
  "isFlippedHorizontal": false,
  "isFlippedVertical": false,
  "isLocked": false,
  "isVisible": true,
  "layerListExpandedType": 0,
  "layers": [
    {
      "class": "shapePath",
      "id": "A4F76CF4-A005-46CF-A1BB-A658178C056B"
    },
    {
      "class": "shapePath",
      "id": "094F4D61-1C51-4C0A-9A26-215221629BC6"
    },
    {
      "class": "shapePath",
      "id": "4C12E3F7-C4BF-4E24-A522-1D6960FBE7C8"
    }
  ],
  "name": "Fill 7",
  "nameIsFixed": false,
  "resizingConstraint": 63,
  "resizingType": 0,
  "rotation": 0,
  "shouldBreakMaskChain": false,
  "style": {
    "_class": "style",
    "endDecorationType": 0,
    "fills": [
      {
        "_class": "fill",
        "color": {
          "_class": "color",
          "alpha": 1,
          "blue": 0.9954422116279602,
          "green": 0.9956298470497131,
          "red": 0.9955094456672668
        },
        "fillType": 0,
        "isEnabled": true,
        "noiseIndex": 0,
        "noiseIntensity": 0,
        "patternFillType": 1,
        "patternTileScale": 1
      }
    ],
    "miterLimit": 10,
    "startDecorationType": 0
  },
  "windingRule": 1
}