{
  "_class": "group",
  "do_objectID": "6E94ACDB-0E35-4382-A14C-A8B5925E0684",
  "exportOptions": {
    "_class": "exportOptions",
    "exportFormats": [
    ],
    "includedLayerIds": [
    ],
    "layerOptions": 0,
    "shouldTrim": false
  },
  "frame": {
    "_class": "rect",
    "constrainProportions": false,
    "height": 31.640625,
    "width": 51.5625,
    "x": 251.5625,
    "y": 0
  },
  "hasClickThrough": false,
  "isFlippedHorizontal": false,
  "isFlippedVertical": false,
  "isLocked": false,
  "isVisible": true,
  "layerListExpandedType": 0,
  "layers": [
    {
      "class": "shapeGroup",
      "id": "A338E943-96E2-43B4-A491-00BAA923075B"
    },
    {
      "class": "shapeGroup",
      "id": "F443BD33-441C-4178-8F1A-D5EA2F74AEE3"
    }
  ],
  "name": "switch (on)",
  "nameIsFixed": false,
  "resizingConstraint": 63,
  "resizingType": 0,
  "rotation": 0,
  "shouldBreakMaskChain": false,
  "style": {
    "_class": "style",
    "blur": {
      "_class": "blur",
      "center": "{0.5, 0.5}",
      "isEnabled": false,
      "motionAngle": 0,
      "radius": 10.11029411764706,
      "type": 0
    },
    "endDecorationType": 0,
    "miterLimit": 10,
    "startDecorationType": 0
  },
  "userInfo": {
    "com.edenvidal.states-for-sketch": {
      "x-states-state-values": {
        "BC315DAF-D4A7-4AC6-898B-8DFBA0A3BFBC": {
          "frame": "{{309, 7}, {51, 31}}",
          "visible": 1
        }
      }
    }
  }
}